{
    "Ar36": {
        "error": 0.0003385707045087295,
        "error_type": "SEM",
        "filter_outliers_dict": {
            "filter_outliers": true,
            "iterations": 1,
            "std_devs": 3,
            "use_iqr_filtering": false,
            "use_standard_deviation_filtering": false
        },
        "fit": "linear",
        "fn": 340,
        "include_baseline_error": true,
        "n": 340,
        "outlier_excluded": [],
        "reviewed": true,
        "user_excluded": [],
        "value": 0.041901201440345634
    },
    "Ar37": {
        "error": 0.0165275707541016,
        "error_type": "SEM",
        "filter_outliers_dict": {
            "filter_outliers": true,
            "iterations": 1,
            "std_devs": 3,
            "use_iqr_filtering": false,
            "use_standard_deviation_filtering": false
        },
        "fit": "linear",
        "fn": 339,
        "include_baseline_error": true,
        "n": 340,
        "outlier_excluded": [
            0
        ],
        "reviewed": true,
        "user_excluded": [],
        "value": 15.672640306125842
    },
    "Ar38": {
        "error": 0.0059421855146206655,
        "error_type": "SEM",
        "filter_outliers_dict": {
            "filter_outliers": true,
            "iterations": 1,
            "std_devs": 3,
            "use_iqr_filtering": false,
            "use_standard_deviation_filtering": false
        },
        "fit": "linear",
        "fn": 339,
        "include_baseline_error": true,
        "n": 340,
        "outlier_excluded": [
            44
        ],
        "reviewed": true,
        "user_excluded": [],
        "value": 0.350419811003196
    },
    "Ar39": {
        "error": 0.009477277760380747,
        "error_type": "SEM",
        "filter_outliers_dict": {
            "filter_outliers": true,
            "iterations": 1,
            "std_devs": 3,
            "use_iqr_filtering": false,
            "use_standard_deviation_filtering": false
        },
        "fit": "linear",
        "fn": 337,
        "include_baseline_error": true,
        "n": 340,
        "outlier_excluded": [
            176,
            41,
            146
        ],
        "reviewed": true,
        "user_excluded": [],
        "value": 12.874181755726656
    },
    "Ar40": {
        "error": 0.03125800736778677,
        "error_type": "SEM",
        "filter_outliers_dict": {
            "filter_outliers": true,
            "iterations": 1,
            "std_devs": 3,
            "use_iqr_filtering": false,
            "use_standard_deviation_filtering": false
        },
        "fit": "parabolic",
        "fn": 339,
        "include_baseline_error": true,
        "n": 340,
        "outlier_excluded": [
            141
        ],
        "reviewed": true,
        "user_excluded": [],
        "value": 31.859805713765113
    }
}