{
    "AX": {
        "error": 0.003960857119716339,
        "error_type": "SEM",
        "filter_outliers_dict": {
            "filter_outliers": true,
            "iterations": 1,
            "std_devs": 2,
            "use_iqr_filtering": false,
            "use_standard_deviation_filtering": false
        },
        "fit": "Average",
        "fn": 57,
        "include_baseline_error": false,
        "n": 60,
        "outlier_excluded": [
            4,
            6,
            46
        ],
        "reviewed": true,
        "user_excluded": [],
        "value": 0.08675344193582996
    },
    "H1": {
        "error": 0.007894273414939968,
        "error_type": "SEM",
        "filter_outliers_dict": {
            "filter_outliers": true,
            "iterations": 1,
            "std_devs": 2,
            "use_iqr_filtering": false,
            "use_standard_deviation_filtering": false
        },
        "fit": "Average",
        "fn": 58,
        "include_baseline_error": false,
        "n": 60,
        "outlier_excluded": [
            1,
            37
        ],
        "reviewed": true,
        "user_excluded": [],
        "value": 0.08180958387474048
    },
    "H2": {
        "error": 0.015294595152201412,
        "error_type": "SEM",
        "filter_outliers_dict": {
            "filter_outliers": true,
            "iterations": 1,
            "std_devs": 2,
            "use_iqr_filtering": false,
            "use_standard_deviation_filtering": false
        },
        "fit": "Average",
        "fn": 58,
        "include_baseline_error": false,
        "n": 60,
        "outlier_excluded": [
            43,
            15
        ],
        "reviewed": true,
        "user_excluded": [],
        "value": -0.10171708110559347
    },
    "L1": {
        "error": 0.014486106979691809,
        "error_type": "SEM",
        "filter_outliers_dict": {
            "filter_outliers": true,
            "iterations": 1,
            "std_devs": 2,
            "use_iqr_filtering": false,
            "use_standard_deviation_filtering": false
        },
        "fit": "Average",
        "fn": 58,
        "include_baseline_error": false,
        "n": 60,
        "outlier_excluded": [
            36,
            13
        ],
        "reviewed": true,
        "user_excluded": [],
        "value": 0.07441647639016397
    },
    "L2(CDD)": {
        "error": 0.0,
        "error_type": "SEM",
        "filter_outliers_dict": {
            "filter_outliers": true,
            "iterations": 1,
            "std_devs": 2
        },
        "fit": "average",
        "value": 0.0
    }
}