{
    "Ar36": {
        "error": 0.00040086193756713734,
        "error_type": "SEM",
        "filter_outliers_dict": {
            "filter_outliers": true,
            "iterations": 1,
            "std_devs": 3,
            "use_iqr_filtering": false,
            "use_standard_deviation_filtering": false
        },
        "fit": "linear",
        "fn": 122,
        "include_baseline_error": true,
        "n": 122,
        "outlier_excluded": [],
        "reviewed": true,
        "user_excluded": [],
        "value": 0.014522645242260821
    },
    "Ar37": {
        "error": 0.006416288770570935,
        "error_type": "SEM",
        "filter_outliers_dict": {
            "filter_outliers": true,
            "iterations": 1,
            "std_devs": 3,
            "use_iqr_filtering": false,
            "use_standard_deviation_filtering": false
        },
        "fit": "linear",
        "fn": 121,
        "include_baseline_error": true,
        "n": 122,
        "outlier_excluded": [
            68
        ],
        "reviewed": true,
        "user_excluded": [],
        "value": 1.833333644434624
    },
    "Ar38": {
        "error": 0.005601866806507959,
        "error_type": "SEM",
        "filter_outliers_dict": {
            "filter_outliers": true,
            "iterations": 1,
            "std_devs": 3,
            "use_iqr_filtering": false,
            "use_standard_deviation_filtering": false
        },
        "fit": "linear",
        "fn": 122,
        "include_baseline_error": true,
        "n": 122,
        "outlier_excluded": [],
        "reviewed": true,
        "user_excluded": [],
        "value": 0.1646067789317653
    },
    "Ar39": {
        "error": 0.013134956786244165,
        "error_type": "SEM",
        "filter_outliers_dict": {
            "filter_outliers": true,
            "iterations": 1,
            "std_devs": 3,
            "use_iqr_filtering": false,
            "use_standard_deviation_filtering": false
        },
        "fit": "linear",
        "fn": 121,
        "include_baseline_error": true,
        "n": 122,
        "outlier_excluded": [
            10
        ],
        "reviewed": true,
        "user_excluded": [],
        "value": 7.722169195400436
    },
    "Ar40": {
        "error": 0.013744842650252992,
        "error_type": "SEM",
        "filter_outliers_dict": {
            "filter_outliers": true,
            "iterations": 1,
            "std_devs": 3,
            "use_iqr_filtering": false,
            "use_standard_deviation_filtering": false
        },
        "fit": "linear",
        "fn": 120,
        "include_baseline_error": true,
        "n": 122,
        "outlier_excluded": [
            105,
            106
        ],
        "reviewed": true,
        "user_excluded": [],
        "value": 19.74673783848534
    },
    "Ar41": {
        "error": 0.028608944476094907,
        "error_type": "SEM",
        "filter_outliers_dict": {
            "filter_outliers": true,
            "iterations": 1,
            "std_devs": 3
        },
        "fit": "average",
        "value": -0.240772530963991
    }
}